{
  "lyrics": [
    {
      "time": 0,
      "lyric": "Legends Never Die",
      "tlyric": "传奇永不湮灭",
      "singer": "Against the Current"
    },
    {
      "time": 12390,
      "lyric": "Legends never die",
      "tlyric": "传奇永不湮灭",
      "remarkIdx": []
    },
    {
      "time": 16270,
      "lyric": "When the world is calling you",
      "tlyric": "当这个世界在呼唤你",
      "remarkIdx": []
    },
    {
      "time": 19420,
      "lyric": "Can you hear them screaming out your name?",
      "tlyric": "你是否能闻世人皆唤你名",
      "remarkIdx": []
    },
    {
      "time": 25920,
      "lyric": "Legends never die",
      "tlyric": "传奇永不湮灭",
      "remarkIdx": []
    },
    {
      "time": 29820,
      "lyric": "They become a part of you",
      "tlyric": "镌刻传奇于己",
      "remarkIdx": []
    },
    {
      "time": 33160,
      "lyric": "Every time you bleed for reaching greatness",
      "tlyric": "浴血谱曲争锋",
      "remarkIdx": []
    },
    {
      "time": 39310,
      "lyric": "Relentless you survive",
      "tlyric": "披星执剑求生",
      "remarkIdx": []
    },
    {
      "time": 43820,
      "lyric": "They never lose hope when everything's cold and the fighting's near",
      "tlyric": "在一切毫无希望与临近的战斗中不失去希望",
      "remarkIdx": []
    },
    {
      "time": 50320,
      "lyric": "It's deep in their bones, they'll run into smoke when the fire is fierce",
      "tlyric": "烈火狷狂侵衣 余烬终将退散",
      "remarkIdx": []
    },
    {
      "time": 57110,
      "lyric": "Oh,  pick yourself up, 'cause",
      "tlyric": "整装待发 为了自己而战",
      "remarkIdx": []
    },
    {
      "time": 59910,
      "lyric": "Legends never die",
      "tlyric": "传奇永不湮灭",
      "remarkIdx": []
    },
    {
      "time": 63908,
      "lyric": "When the world is calling you",
      "tlyric": "当这个世界需要你",
      "remarkIdx": []
    },
    {
      "time": 67719,
      "lyric": "Can you hear them screaming out your name?",
      "tlyric": "世人皆唤你名",
      "remarkIdx": []
    },
    {
      "time": 74009,
      "lyric": "Legends never die",
      "tlyric": "传奇永不湮灭",
      "remarkIdx": []
    },
    {
      "time": 77920,
      "lyric": "They become a part of you",
      "tlyric": "镌刻传奇于己",
      "remarkIdx": []
    },
    {
      "time": 81409,
      "lyric": "Every time you bleed for reaching greatness",
      "tlyric": "浴血谱曲传奇",
      "remarkIdx": []
    },
    {
      "time": 87709,
      "lyric": "Legends never die",
      "tlyric": "再以永恒为基",
      "remarkIdx": []
    },
    {
      "time": 91500,
      "lyric": "They're written down in eternity",
      "tlyric": "铸成传奇不熄",
      "remarkIdx": []
    },
    {
      "time": 94989,
      "lyric": "But you'll never see the price it costs the scars collected all their lives",
      "tlyric": "可叹伤痕累然 不见埋骨之川",
      "remarkIdx": []
    },
    {
      "time": 105340,
      "lyric": "When everything's lost, they pick up their hearts and avenge defeat",
      "tlyric": "天以万物夺之 便以此身为敌",
      "remarkIdx": []
    },
    {
      "time": 112269,
      "lyric": "Before it all starts, they suffer through harm just to touch a dream",
      "tlyric": "回首向来当年 不过逐梦少年",
      "remarkIdx": []
    },
    {
      "time": 119009,
      "lyric": "Oh, pick yourself up 'cause",
      "tlyric": "整装待发 为了自己而战",
      "remarkIdx": []
    },
    {
      "time": 121959,
      "lyric": "Legends never die",
      "tlyric": "传奇永不湮灭",
      "remarkIdx": []
    },
    {
      "time": 125799,
      "lyric": "When the world is calling you",
      "tlyric": "当这个世界需要你",
      "remarkIdx": []
    },
    {
      "time": 129188,
      "lyric": "Can you hear them screaming out your name?",
      "tlyric": "你能听见世人皆唤你名吗？",
      "remarkIdx": []
    },
    {
      "time": 135539,
      "lyric": "Legends never die",
      "tlyric": "传奇永不湮灭",
      "remarkIdx": []
    },
    {
      "time": 139389,
      "lyric": "They become a part of you",
      "tlyric": "镌刻传奇于己",
      "remarkIdx": []
    },
    {
      "time": 142839,
      "lyric": "Every time you bleed for reaching greatness",
      "tlyric": "浴血谱曲传奇",
      "remarkIdx": []
    },
    {
      "time": 149179,
      "lyric": "Legends never die",
      "tlyric": "铸成传奇不熄",
      "remarkIdx": []
    },
    {
      "time": 155669,
      "lyric": "When the world is calling out your name",
      "tlyric": "世人皆唤你名",
      "remarkIdx": []
    },
    {
      "time": 162910,
      "lyric": "Begging you to fight",
      "tlyric": "祈求剑刃再起",
      "remarkIdx": []
    },
    {
      "time": 170960,
      "lyric": "Pick yourself up once more",
      "tlyric": "再次振作起来",
      "remarkIdx": []
    },
    {
      "time": 174399,
      "lyric": "pick yourself up, 'cause",
      "tlyric": "为了自己而战",
      "remarkIdx": []
    },
    {
      "time": 177099,
      "lyric": "Legends never die",
      "tlyric": "传奇永不湮灭",
      "remarkIdx": []
    },
    {
      "time": 180838,
      "lyric": "When the world is calling you",
      "tlyric": "当这个世界需要你",
      "remarkIdx": []
    },
    {
      "time": 184338,
      "lyric": "Can you hear them screaming out your name?",
      "tlyric": "世人皆唤你名",
      "remarkIdx": []
    },
    {
      "time": 190278,
      "lyric": "Legends never die",
      "tlyric": "再以永恒为基",
      "remarkIdx": []
    },
    {
      "time": 194229,
      "lyric": "They become a part of you",
      "tlyric": "镌刻传奇于己",
      "remarkIdx": []
    },
    {
      "time": 197979,
      "lyric": "Every time you bleed for reaching greatness",
      "tlyric": "三千热血洒尽",
      "remarkIdx": []
    },
    {
      "time": 204369,
      "lyric": "Legends never die",
      "tlyric": "传奇永不湮灭",
      "remarkIdx": []
    }
  ],
  "code": 200,
  "apiInfo": {
    "sgc": false,
    "sfy": false,
    "qfy": false,
    "transUser": {
      "id": 2154634,
      "status": 99,
      "demand": 1,
      "userid": 119147969,
      "nickname": "雨归i",
      "uptime": 1509072601035
    },
    "lyricUser": {
      "id": 2154624,
      "status": 99,
      "demand": 0,
      "userid": 97627455,
      "nickname": "FelixCooper",
      "uptime": 1509072601035
    },
    "lrc": {
      "version": 37,
      "lyric": "[00:00.000] 作词 : Alex Seaver\n[00:01.000] 作曲 : 拳头游戏、Alex Seaver of Mako、Justin Tranter、Oliver\n[00:12.390]Legends never die\n[00:16.270]When the world is calling you\n[00:19.420]Can you hear them screaming out your name?\n[00:25.920]Legends never die\n[00:29.820]They become a part of you\n[00:33.160]Every time you bleed for reaching greatness\n[00:39.310]Relentless you survive\n[00:43.820]They never lose hope when everything's cold and the fighting's near\n[00:50.320]It's deep in their bones, they'll run into smoke when the fire is fierce\n[00:57.110]Oh,  pick yourself up, 'cause\n[00:59.910]Legends never die\n[01:03.908]When the world is calling you\n[01:07.719]Can you hear them screaming out your name?\n[01:14.009]Legends never die\n[01:17.920]They become a part of you\n[01:21.409]Every time you bleed for reaching greatness\n[01:27.709]Legends never die\n[01:31.500]They're written down in eternity\n[01:34.989]But you'll never see the price it costs the scars collected all their lives\n[01:45.340]When everything's lost, they pick up their hearts and avenge defeat\n[01:52.269]Before it all starts, they suffer through harm just to touch a dream\n[01:59.009]Oh, pick yourself up 'cause\n[02:01.959]Legends never die\n[02:05.799]When the world is calling you\n[02:09.188]Can you hear them screaming out your name?\n[02:15.539]Legends never die\n[02:19.389]They become a part of you\n[02:22.839]Every time you bleed for reaching greatness\n[02:29.179]Legends never die\n[02:35.669]When the world is calling out your name\n[02:42.910]Begging you to fight\n[02:50.960]Pick yourself up once more\n[02:54.399]pick yourself up, 'cause\n[02:57.099]Legends never die\n[03:00.838]When the world is calling you\n[03:04.338]Can you hear them screaming out your name?\n[03:10.278]Legends never die\n[03:14.229]They become a part of you\n[03:17.979]Every time you bleed for reaching greatness\n[03:24.369]Legends never die\n"
    },
    "tlyric": {
      "version": 30,
      "lyric": "[00:12.390]传奇永不湮灭\n[00:16.270]当这个世界在呼唤你\n[00:19.420]你是否能闻世人皆唤你名\n[00:25.920]传奇永不湮灭\n[00:29.820]镌刻传奇于己\n[00:33.160]浴血谱曲争锋\n[00:39.310]披星执剑求生\n[00:43.820]在一切毫无希望与临近的战斗中不失去希望\n[00:50.320]烈火狷狂侵衣 余烬终将退散\n[00:57.110]整装待发 为了自己而战\n[00:59.910]传奇永不湮灭\n[01:03.908]当这个世界需要你\n[01:07.719]世人皆唤你名\n[01:14.009]传奇永不湮灭\n[01:17.920]镌刻传奇于己\n[01:21.409]浴血谱曲传奇\n[01:27.709]再以永恒为基\n[01:31.500]铸成传奇不熄\n[01:34.989]可叹伤痕累然 不见埋骨之川\n[01:45.340]天以万物夺之 便以此身为敌\n[01:52.269]回首向来当年 不过逐梦少年\n[01:59.009]整装待发 为了自己而战\n[02:01.959]传奇永不湮灭\n[02:05.799]当这个世界需要你\n[02:09.188]你能听见世人皆唤你名吗？\n[02:15.539]传奇永不湮灭\n[02:19.389]镌刻传奇于己\n[02:22.839]浴血谱曲传奇\n[02:29.179]铸成传奇不熄\n[02:35.669]世人皆唤你名\n[02:42.910]祈求剑刃再起\n[02:50.960]再次振作起来\n[02:54.399]为了自己而战\n[02:57.099]传奇永不湮灭\n[03:00.838]当这个世界需要你\n[03:04.338]世人皆唤你名\n[03:10.278]再以永恒为基\n[03:14.229]镌刻传奇于己\n[03:17.979]三千热血洒尽\n[03:24.369]传奇永不湮灭"
    },
    "code": 200
  }
}